tray_runner/__init__.py
tray_runner/__main__.py
tray_runner/cli/__init__.py
tray_runner/cli/__main__.py
tray_runner/common_utils/__init__.py
tray_runner/common_utils/common.py
tray_runner/common_utils/qt.py
tray_runner/config.py
tray_runner/constants.py
tray_runner/gui/__init__.py
tray_runner/gui/__main__.py
tray_runner/gui/command_dialog.py
tray_runner/gui/command_dialog.ui
tray_runner/gui/constants.py
tray_runner/gui/icons/ikonate/cancel.svg
tray_runner/gui/icons/ikonate/circle.svg
tray_runner/gui/icons/ikonate/exit.svg
tray_runner/gui/icons/ikonate/ok-circle.svg
tray_runner/gui/icons/ikonate/qr.svg
tray_runner/gui/icons/ikonate/settings.svg
tray_runner/gui/icons/terminal--exclamation.png
tray_runner/gui/icons/terminal-medium.ico
tray_runner/gui/icons/terminal-medium.png
tray_runner/gui/settings_dialog.py
tray_runner/gui/settings_dialog.ui
tray_runner/utils.py
tray_runner-0.4.1.dist-info/entry_points.txt
tray_runner-0.4.1.dist-info/LICENSE
tray_runner-0.4.1.dist-info/WHEEL
tray_runner-0.4.1.dist-info/METADATA
tray_runner-0.4.1.dist-info/RECORD
