Metadata-Version: 2.1
Name: tray-runner
Version: 0.4.1
Summary: Tool to run and restart commands, so they can be continuously executed. The application can be run from the console or using a tray icon.
Home-page: https://github.com/okelet/tray-runner
Author: Juan A. S.
Author-email: okelet@gmail.com
Requires-Python: >=3.10,<3.11
Classifier: Programming Language :: Python :: 3
Classifier: Programming Language :: Python :: 3.10
Requires-Dist: Babel (>=2.10.1,<3.0.0)
Requires-Dist: PySide6-Essentials (>=6.3.0,<7.0.0)
Requires-Dist: click (>=8.1.3,<9.0.0)
Requires-Dist: croniter (>=1.3.5,<2.0.0)
Requires-Dist: pydantic (>=1.9.1,<2.0.0)
Requires-Dist: python-dateutil (>=2.8.2,<3.0.0)
Requires-Dist: python-slugify (>=6.1.2,<7.0.0)
Requires-Dist: pywin32 (>=304,<305); sys_platform == "win32"
Requires-Dist: winshell (>=0.6,<0.7); sys_platform == "win32"
Project-URL: Documentation, https://github.com/okelet/tray-runner
Project-URL: Repository, https://github.com/okelet/tray-runner
